hladr4pred2/blast_binaries/linux/blastp
hladr4pred2/blast_binaries/mac/blastp
hladr4pred2/blast_binaries/windows/blastp.exe
hladr4pred2/blast_binaries/windows/nghttp2.dll
hladr4pred2/blast_db/train.phr
hladr4pred2/blast_db/train.pin
hladr4pred2/blast_db/train.pog
hladr4pred2/blast_db/train.psd
hladr4pred2/blast_db/train.psi
hladr4pred2/blast_db/train.psq
hladr4pred2/python_scripts/__init__.py
hladr4pred2/python_scripts/hladr4pred2.py
hladr4pred2-1.0.0.dist-info/METADATA
hladr4pred2-1.0.0.dist-info/WHEEL
hladr4pred2-1.0.0.dist-info/entry_points.txt
hladr4pred2-1.0.0.dist-info/top_level.txt
hladr4pred2-1.0.0.dist-info/RECORD
