Metadata-Version: 2.1
Name: hladr4pred2
Version: 1.0.0
Summary: A computational approach to predict HLA-DRB1-04:01 binders using the sequence information of the peptides.
Home-page: https://github.com/sumeetpatiyal/hladr4pred2
Author: Sumeet patiyal
Author-email: sumeetp@iiitd.ac.in
Requires-Python: >=3.8
Requires-Dist: numpy
Requires-Dist: pandas
Requires-Dist: onnxruntime
Requires-Dist: scikit-learn
Requires-Dist: tqdm
